cbe_verification_sdk/__init__.py
cbe_verification_sdk/client.py
cbe_verification_sdk-1.4.0.dist-info/LICENSE
cbe_verification_sdk-1.4.0.dist-info/METADATA
cbe_verification_sdk-1.4.0.dist-info/WHEEL
cbe_verification_sdk-1.4.0.dist-info/top_level.txt
cbe_verification_sdk-1.4.0.dist-info/RECORD
