Metadata-Version: 2.2
Name: cbe-verification-sdk
Version: 1.4.0
Summary: SDK for CBE Transaction Verification API
Home-page: https://github.com/NaodYeshiwas/CBE-Verification-API
Author: Naod Yeshiwas
Author-email: yegnadevelopers@gmail.com
Classifier: Programming Language :: Python :: 3
Classifier: License :: OSI Approved :: MIT License
Classifier: Operating System :: OS Independent
Requires-Python: >=3.7
License-File: LICENSE
Requires-Dist: requests>=2.25.0
Requires-Dist: PyPDF2>=3.0.0
Dynamic: author
Dynamic: author-email
Dynamic: classifier
Dynamic: description
Dynamic: description-content-type
Dynamic: home-page
Dynamic: requires-dist
Dynamic: requires-python
Dynamic: summary
